setup.cfg
setup.py
seline_test_dist.egg-info/PKG-INFO
seline_test_dist.egg-info/SOURCES.txt
seline_test_dist.egg-info/dependency_links.txt
seline_test_dist.egg-info/not-zip-safe
seline_test_dist.egg-info/top_level.txt
test_distribution/BinomialDist.py
test_distribution/GeneralDistribution.py
test_distribution/__init__.py