Metadata-Version: 1.0
Name: seline-test-dist
Version: 0.1
Summary: BinomialDistribution
Home-page: UNKNOWN
Author: UNKNOWN
Author-email: UNKNOWN
License: UNKNOWN
Platform: UNKNOWN
